[{"id":"dbc89c3e1ce4f450","type":"inject","z":"cb6b757125998343","name":"","props":[{"p":"payload"},{"p":"topic","vt":"str"}],"repeat":"","crontab":"","once":false,"onceDelay":0.1,"topic":"","payload":"off","payloadType":"str","x":410,"y":240,"wires":[["b060a1f3badcc99a"]]},{"id":"c88c0ace10d27171","type":"debug","z":"cb6b757125998343","name":"debug 14","active":true,"tosidebar":true,"console":false,"tostatus":false,"complete":"false","statusVal":"","statusType":"auto","x":660,"y":480,"wires":[]},{"id":"6c87eb59c27c6a4c","type":"mqtt in","z":"cb6b757125998343","name":"","topic":"device1/light","qos":"2","datatype":"auto-detect","broker":"e04e4ce614fd40d0","nl":false,"rap":true,"rh":0,"inputs":0,"x":490,"y":480,"wires":[["c88c0ace10d27171"]]},{"id":"b060a1f3badcc99a","type":"mqtt out","z":"cb6b757125998343","name":"","topic":"device1/led","qos":"","retain":"","respTopic":"","contentType":"","userProps":"","correl":"","expiry":"","broker":"e04e4ce614fd40d0","x":670,"y":280,"wires":[]},{"id":"5ab8ef23312cfbbe","type":"inject","z":"cb6b757125998343","name":"","props":[{"p":"payload"},{"p":"topic","vt":"str"}],"repeat":"","crontab":"","once":false,"onceDelay":0.1,"topic":"","payload":"on","payloadType":"str","x":410,"y":280,"wires":[["b060a1f3badcc99a"]]},{"id":"6e817a33a55e12bd","type":"inject","z":"cb6b757125998343","name":"","props":[{"p":"payload"},{"p":"topic","vt":"str"}],"repeat":"","crontab":"","once":false,"onceDelay":0.1,"topic":"","payload":"up","payloadType":"str","x":410,"y":320,"wires":[["b060a1f3badcc99a"]]},{"id":"d9b5762ef9e7c2d6","type":"inject","z":"cb6b757125998343","name":"","props":[{"p":"payload"},{"p":"topic","vt":"str"}],"repeat":"","crontab":"","once":false,"onceDelay":0.1,"topic":"","payload":"down","payloadType":"str","x":410,"y":360,"wires":[["b060a1f3badcc99a"]]},{"id":"35858665f1fce213","type":"inject","z":"cb6b757125998343","name":"","props":[{"p":"payload"},{"p":"topic","vt":"str"}],"repeat":"","crontab":"","once":false,"onceDelay":0.1,"topic":"","payload":"wave","payloadType":"str","x":410,"y":400,"wires":[["b060a1f3badcc99a"]]},{"id":"cb867449a41710dc","type":"comment","z":"cb6b757125998343","name":"basic interatcion","info":"","x":560,"y":160,"wires":[]},{"id":"060df0a45b383d4f","type":"aedes broker","z":"cb6b757125998343","name":"","mqtt_port":1883,"mqtt_ws_bind":"port","mqtt_ws_port":"","mqtt_ws_path":"","cert":"","key":"","certname":"","keyname":"","persistence_bind":"memory","dburl":"","usetls":false,"x":790,"y":160,"wires":[[],[]]},{"id":"2155641799bad1c2","type":"comment","z":"cb6b757125998343","name":"Our Broker","info":"","x":760,"y":120,"wires":[]},{"id":"e04e4ce614fd40d0","type":"mqtt-broker","name":"","broker":"192.168.0.41","port":1883,"clientid":"","autoConnect":true,"usetls":false,"protocolVersion":4,"keepalive":60,"cleansession":true,"autoUnsubscribe":true,"birthTopic":"","birthQos":"0","birthRetain":"false","birthPayload":"","birthMsg":{},"closeTopic":"","closeQos":"0","closeRetain":"false","closePayload":"","closeMsg":{},"willTopic":"","willQos":"0","willRetain":"false","willPayload":"","willMsg":{},"userProps":"","sessionExpiry":""}]